qstrings/Q.py
qstrings/__init__.py
qstrings/api.py
qstrings/cli.py
qstrings/config.py
qstrings-0.4.2.dist-info/METADATA
qstrings-0.4.2.dist-info/WHEEL
qstrings-0.4.2.dist-info/entry_points.txt
qstrings-0.4.2.dist-info/RECORD
