Metadata-Version: 2.4
Name: qstrings
Version: 0.4.2
Summary: Q-strings: query anything
Requires-Python: >=3.12
Requires-Dist: autoregistry>=1.1.2
Requires-Dist: duckdb>=1.3
Requires-Dist: fsspec>=2025.9.0
Requires-Dist: sqlglot>=27.6.0
Provides-Extra: ai
Requires-Dist: openai>=1.101.0; extra == 'ai'
Provides-Extra: all
Requires-Dist: cyclopts>=3.23.0; extra == 'all'
Requires-Dist: openai>=1.101.0; extra == 'all'
Requires-Dist: robyn>=0.72.0; extra == 'all'
Provides-Extra: api
Requires-Dist: robyn>=0.72.0; extra == 'api'
Provides-Extra: cli
Requires-Dist: cyclopts>=3.23.0; extra == 'cli'
